decopy/__init__.py
decopy/test.py
decopy-0.0.3.dist-info/LICENSE
decopy-0.0.3.dist-info/METADATA
decopy-0.0.3.dist-info/WHEEL
decopy-0.0.3.dist-info/top_level.txt
decopy-0.0.3.dist-info/RECORD
