Metadata-Version: 2.1
Name: decopy
Version: 0.0.3
Summary: This is a module for decoration in python cli runtime environment.
Home-page: https://github.com/yogeshkartik/decopy/
Author: yogesh kartik
Author-email: kartikyogesh2004@gmail.com
License: UNKNOWN
Platform: UNKNOWN
Classifier: Programming Language :: Python :: 3
Classifier: License :: OSI Approved :: Apache Software License
Classifier: Operating System :: OS Independent
Requires-Python: >=3.6
